setup.py
LinkScanner/LinkScraperMultithreaded.py
LinkScanner/__init__.py
LinkScanner.egg-info/PKG-INFO
LinkScanner.egg-info/SOURCES.txt
LinkScanner.egg-info/dependency_links.txt
LinkScanner.egg-info/requires.txt
LinkScanner.egg-info/top_level.txt