Metadata-Version: 1.0
Name: LinkScanner
Version: 1.1
Summary: Follow links from website to website.
Home-page: https://github.com/themooer1/LinkScanner
Author: Eugene Wolffe
Author-email: fluffy1781@gmail.com
License: GPL
Platform: UNKNOWN
